{
  "Description": "Apple Music 연동", 
  "Localization": {
    "Volume Down": "음량 감소", 
    "Volume Up": "음량 증가"
  }, 
  "Name": "Apple Music", 
  "com.elgato.applemusic.love": {
    "Name": "좋아요", 
    "States": [
      {
        "Name": "좋아요"
      }, 
      {
        "Name": "좋아요 해제"
      }
    ], 
    "Tooltip": "현재 트랙에 좋아요를 표시합니다"
  }, 
  "com.elgato.applemusic.next": {
    "Name": "다음 트랙", 
    "Tooltip": "다음 트랙 재생"
  }, 
  "com.elgato.applemusic.play": {
    "Name": "재생/일시정지", 
    "States": [
      {
        "Name": "재생"
      }, 
      {
        "Name": "일시정지"
      }
    ], 
    "Tooltip": "재생/일시정지"
  }, 
  "com.elgato.applemusic.previous": {
    "Name": "이전 트랙", 
    "Tooltip": "이전 트랙 재생"
  }, 
  "com.elgato.applemusic.shuffle": {
    "Name": "임의 재생", 
    "States": [
      {
        "Name": "켬"
      }, 
      {
        "Name": "끔"
      }
    ], 
    "Tooltip": "이 기기에 대한 무작위 재생 켬/끔"
  }, 
  "com.elgato.applemusic.volume": {
    "Name": "음량", 
    "Tooltip": "음량을 변경합니다"
  }
}
